libzim.cpython-311-aarch64-linux-gnu.so
libzim/__init__.pyi
libzim/libwrapper.cpp
libzim/libwrapper.h
libzim/libzim.cpp
libzim/libzim.h
libzim/libzim.pyx
libzim/libzim.so.9
libzim/libzim_api.h
libzim/reader.pyi
libzim/search.pyi
libzim/suggestion.pyi
libzim/version.pyi
libzim/writer.pyi
libzim/zim.pxd
libzim-3.8.0.dist-info/METADATA
libzim-3.8.0.dist-info/WHEEL
libzim-3.8.0.dist-info/top_level.txt
libzim-3.8.0.dist-info/RECORD
libzim-3.8.0.dist-info/licenses/LICENSE
