Metadata-Version: 2.4
Name: libzim
Version: 3.8.0
Summary: A python-facing API for creating and interacting with ZIM files
Author-email: openZIM <dev@kiwix.org>
License-Expression: GPL-3.0-or-later
Project-URL: Homepage, https://github.com/openzim/python-libzim
Project-URL: Donate, https://www.kiwix.org/en/support-us/
Classifier: Development Status :: 5 - Production/Stable
Classifier: Topic :: Utilities
Classifier: Topic :: Software Development :: Libraries
Classifier: Topic :: Software Development :: Libraries :: Python Modules
Classifier: Topic :: System :: Archiving
Classifier: Topic :: System :: Archiving :: Compression
Classifier: Topic :: System :: Archiving :: Mirroring
Classifier: Topic :: System :: Archiving :: Backup
Classifier: Intended Audience :: Developers
Classifier: Programming Language :: Cython
Classifier: Programming Language :: Python :: 3
Classifier: Programming Language :: Python :: 3.10
Classifier: Programming Language :: Python :: 3.11
Classifier: Programming Language :: Python :: 3.12
Classifier: Programming Language :: Python :: 3.13
Classifier: Programming Language :: Python :: 3.14
Classifier: Typing :: Stubs Only
Classifier: Operating System :: MacOS
Classifier: Operating System :: POSIX
Requires-Python: <3.15,>=3.10
License-File: LICENSE
Provides-Extra: scripts
Requires-Dist: invoke==2.2.0; extra == "scripts"
Provides-Extra: lint
Requires-Dist: black==25.9.0; extra == "lint"
Requires-Dist: ruff==0.14.3; extra == "lint"
Requires-Dist: libzim; extra == "lint"
Requires-Dist: libzim[build]; extra == "lint"
Provides-Extra: check
Requires-Dist: pyright==1.1.407; extra == "check"
Requires-Dist: libzim; extra == "check"
Requires-Dist: libzim[build]; extra == "check"
Requires-Dist: libzim[test]; extra == "check"
Requires-Dist: types-setuptools; extra == "check"
Provides-Extra: test
Requires-Dist: pytest==8.4.2; extra == "test"
Requires-Dist: coverage==7.11.0; extra == "test"
Requires-Dist: libzim[build]; extra == "test"
Provides-Extra: build
Requires-Dist: setuptools==80.9.0; extra == "build"
Requires-Dist: wheel==0.45.1; extra == "build"
Requires-Dist: cython==3.1.6; extra == "build"
Requires-Dist: delocate==0.13.0; platform_system == "Windows" and extra == "build"
Provides-Extra: docs
Requires-Dist: mkdocs==1.6.1; extra == "docs"
Requires-Dist: mkdocstrings-python==1.18.2; extra == "docs"
Requires-Dist: mkdocs-material==9.6.23; extra == "docs"
Requires-Dist: pymdown-extensions==10.16.1; extra == "docs"
Requires-Dist: mkdocs-gen-files==0.5.0; extra == "docs"
Requires-Dist: mkdocs-literate-nav==0.6.2; extra == "docs"
Requires-Dist: mkdocs-include-markdown-plugin==7.2.0; extra == "docs"
Requires-Dist: griffe==1.14.0; extra == "docs"
Provides-Extra: dev
Requires-Dist: pre-commit==4.3.0; extra == "dev"
Requires-Dist: ipython==9.6.0; extra == "dev"
Requires-Dist: types-setuptools; extra == "dev"
Requires-Dist: libzim[scripts]; extra == "dev"
Requires-Dist: libzim[lint]; extra == "dev"
Requires-Dist: libzim[test]; extra == "dev"
Requires-Dist: libzim[check]; extra == "dev"
Requires-Dist: libzim[build]; extra == "dev"
Requires-Dist: libzim[docs]; extra == "dev"
Dynamic: license-file
